runflow/__init__.py
runflow/__main__.py
runflow/autoloader.py
runflow/cli.py
runflow/core.py
runflow/errors.py
runflow/hcl2.lark
runflow/hcl2.py
runflow/hcl2_parser.py
runflow/registry.py
runflow/run.py
runflow/utils.py
runflow/community/__init__.py
runflow/community/docker.py
runflow/community/notion.py
runflow/community/papermill.py
runflow/community/pushbullet.py
runflow/community/qrcode.py
runflow/community/rss.py
runflow/community/slack.py
runflow/community/telegram.py
runflow/contribs/__init__.py
runflow/contribs/bash.py
runflow/contribs/file.py
runflow/contribs/http.py
runflow/contribs/mail.py
runflow/contribs/sql.py
runflow/contribs/template.py
runflow-0.10.0.dist-info/LICENSE
runflow-0.10.0.dist-info/METADATA
runflow-0.10.0.dist-info/WHEEL
runflow-0.10.0.dist-info/entry_points.txt
runflow-0.10.0.dist-info/top_level.txt
runflow-0.10.0.dist-info/RECORD
