Metadata-Version: 2.1
Name: runflow
Version: 0.10.0
Summary: Define and run your workflows
Home-page: https://github.com/soasme/runflow
Author: Ju Lin
Author-email: soasme@gmail.com
License: UNKNOWN
Project-URL: Bug Tracker, https://github.com/soasme/runflow/issues
Platform: UNKNOWN
Classifier: Topic :: Utilities
Classifier: Topic :: Software Development :: Libraries
Classifier: Programming Language :: Python :: 3
Classifier: License :: OSI Approved :: Apache Software License
Classifier: Operating System :: OS Independent
Requires-Python: >=3.7
License-File: LICENSE
Requires-Dist: networkx (>=2.0)
Requires-Dist: httpx (>=0.15.0)
Requires-Dist: python-decouple (>=3.0)
Requires-Dist: lark (>=0.10.1)
Requires-Dist: python-dateutil (>=2.8.1)
Requires-Dist: SQLAlchemy (>=1.4.0)
Requires-Dist: fsspec (>=2021.4.0)
Requires-Dist: tenacity (>=7.0.0)
Requires-Dist: attrs (>=21.2.0)
Provides-Extra: all
Requires-Dist: docker (>=5.0.0) ; extra == 'all'
Requires-Dist: notion-client (>=0.4.0) ; extra == 'all'
Requires-Dist: feedparser (>=6.0.2) ; extra == 'all'
Requires-Dist: slack-sdk (>=3.5.0) ; extra == 'all'
Requires-Dist: aiohttp (>=3.7.0) ; extra == 'all'
Requires-Dist: papermill (>=2.3.0) ; extra == 'all'
Requires-Dist: jupyterlab (>=3.0.0) ; extra == 'all'
Requires-Dist: pushbullet.py (>=0.12.0) ; extra == 'all'
Requires-Dist: pygraphviz (>=1.5) ; extra == 'all'
Requires-Dist: qrcode[pil] (>=7.0) ; extra == 'all'
Requires-Dist: python-telegram-bot (~=13.0) ; extra == 'all'
Provides-Extra: docker
Requires-Dist: docker (>=5.0.0) ; extra == 'docker'
Provides-Extra: notion
Requires-Dist: notion-client (>=0.4.0) ; extra == 'notion'
Provides-Extra: papermill
Requires-Dist: papermill (>=2.3.0) ; extra == 'papermill'
Requires-Dist: jupyterlab (>=3.0.0) ; extra == 'papermill'
Provides-Extra: pushbullet
Requires-Dist: pushbullet.py (>=0.12.0) ; extra == 'pushbullet'
Provides-Extra: pygraphviz
Requires-Dist: pygraphviz (>=1.5) ; extra == 'pygraphviz'
Provides-Extra: qrcode
Requires-Dist: qrcode[pil] (>=7.0) ; extra == 'qrcode'
Provides-Extra: rss
Requires-Dist: feedparser (>=6.0.2) ; extra == 'rss'
Provides-Extra: slack
Requires-Dist: slack-sdk (>=3.5.0) ; extra == 'slack'
Requires-Dist: aiohttp (>=3.7.0) ; extra == 'slack'
Provides-Extra: telegram
Requires-Dist: python-telegram-bot (~=13.0) ; extra == 'telegram'
